insightxnsdk/__init__.py
insightxnsdk-0.1.6.dist-info/METADATA
insightxnsdk-0.1.6.dist-info/WHEEL
insightxnsdk-0.1.6.dist-info/top_level.txt
insightxnsdk-0.1.6.dist-info/RECORD
