Metadata-Version: 2.1
Name: insightxnsdk
Version: 0.1.6
Summary: sdk for insightxn
Home-page: https://gitee.com/ZeroSeeker/fastaliyun
Author: ZeroSeeker
Author-email: zeroseeker@foxmail.com
Classifier: Programming Language :: Python :: 3
Classifier: License :: OSI Approved :: MIT License
Classifier: Operating System :: OS Independent
Requires-Dist: envx >=1.0.1
Requires-Dist: lazysdk >=0.1.101
